LeptonInjector/LeptonInjector.cpython-312-x86_64-linux-gnu.so
LeptonInjector/__init__.py
LeptonInjector/resources/earthparams/densities/PREM_mmc.dat
LeptonInjector/resources/earthparams/densities/mmc.dat
LeptonInjector/resources/earthparams/densities/PREM.dat
LeptonInjector/resources/earthparams/densities/FLATCORE_5.568.dat
LeptonInjector/resources/earthparams/densities/README
LeptonInjector/resources/earthparams/materials/Standard.dat
LeptonInjector/resources/earthparams/materials/Fe_Core.dat
LeptonInjector/resources/earthparams/materials/Standard_RockIce.dat
LeptonInjector/resources/earthparams/materials/SiO2_Mantle.dat
LeptonInjector/resources/earthparams/materials/Standard_Air.dat
LeptonInjector/resources/earthparams/old_formats/PREM_mmc.dat
LeptonInjector/resources/earthparams/old_formats/PREM_legacy.dat
LeptonInjector/resources/earthparams/old_formats/PREM_legacy_mmcnewice.dat
leptoninjector.libs/libaec-91f0ca0f.so.0.0.8
leptoninjector.libs/libcfitsio-b4c37dff.so.7.3.47
leptoninjector.libs/libbz2-e34b29ae.so.1.0.6
leptoninjector.libs/libphotospline-7df4e428.so.2.3.1
leptoninjector.libs/libhdf5-b5e70f84.so.103.1.0
leptoninjector.libs/libsz-0deeef7d.so.2.0.1
leptoninjector-1.1.0.dist-info/WHEEL
leptoninjector-1.1.0.dist-info/METADATA
leptoninjector-1.1.0.dist-info/RECORD
leptoninjector-1.1.0.dist-info/licenses/LICENSE
