Metadata-Version: 2.2
Name: LeptonInjector
Version: 1.1.0
Summary: Generates neutrino events for large volume Cherenkov telescopes
Author: IceCube Collaboration
License:                    GNU LESSER GENERAL PUBLIC LICENSE
Classifier: Programming Language :: Python :: 3
Classifier: Programming Language :: C++
Classifier: License :: OSI Approved :: GNU General Public License v3 (GPLv3)
Classifier: Topic :: Scientific/Engineering :: Physics
Requires-Python: >=3.8
Requires-Dist: numpy
Provides-Extra: hdf5
Requires-Dist: h5py; extra == "hdf5"
